compushady/__init__.py
compushady/config.py
compushady/formats.py
compushady/backends/d3d12.cp311-win_amd64.pyd
compushady/backends/dxc.cp311-win_amd64.pyd
compushady/backends/dxcompiler.dll
compushady/backends/dxil.dll
compushady/backends/vulkan.cp311-win_amd64.pyd
compushady/shaders/__init__.py
compushady/shaders/hlsl.py
compushady/shaders/msl.py
compushady-0.17.5.dist-info/LICENSE
compushady-0.17.5.dist-info/METADATA
compushady-0.17.5.dist-info/WHEEL
compushady-0.17.5.dist-info/top_level.txt
compushady-0.17.5.dist-info/RECORD
