Metadata-Version: 2.1
Name: compushady
Version: 0.17.5
Summary: The compushady GPU Compute module
Home-page: https://github.com/rdeioris/compushady
Author: Roberto De Ioris
Author-email: roberto.deioris@gmail.com
License-File: LICENSE
